setup.py
initclass_mahe/__init__.py.py
initclass_mahe.egg-info/PKG-INFO
initclass_mahe.egg-info/SOURCES.txt
initclass_mahe.egg-info/dependency_links.txt
initclass_mahe.egg-info/not-zip-safe
initclass_mahe.egg-info/top_level.txt