Metadata-Version: 1.0
Name: initclass-mahe
Version: 0.1
Summary: Mahe\python package
Home-page: UNKNOWN
Author: Mahe
Author-email: mayyanar@grundfos.com
License: GPL
Platform: UNKNOWN
